tqdm_multiprocessing/__init__.py
tqdm_multiprocessing/mapper.py
tqdm_multiprocessing-0.1.2.dist-info/LICENSE
tqdm_multiprocessing-0.1.2.dist-info/METADATA
tqdm_multiprocessing-0.1.2.dist-info/WHEEL
tqdm_multiprocessing-0.1.2.dist-info/top_level.txt
tqdm_multiprocessing-0.1.2.dist-info/RECORD
