Metadata-Version: 2.1
Name: tqdm_multiprocessing
Version: 0.1.2
Home-page: https://github.com/medcognetics/tqdm-multiprocessing
Author: Scott Chase Waggener
Requires-Python: >=3.8
License-File: LICENSE
Requires-Dist: tqdm
Provides-Extra: dist
Requires-Dist: build ; extra == 'dist'
Requires-Dist: twine ; extra == 'dist'
Provides-Extra: quality
Requires-Dist: autoflake ; extra == 'quality'
Requires-Dist: autopep8 ; extra == 'quality'
Requires-Dist: black ; extra == 'quality'
Requires-Dist: flake8 ; extra == 'quality'
Requires-Dist: isort ; extra == 'quality'
Provides-Extra: test
Requires-Dist: pytest ; extra == 'test'
Requires-Dist: pytest-mock ; extra == 'test'
Requires-Dist: pytest-cov ; extra == 'test'
Requires-Dist: coverage ; extra == 'test'
